tdbudget/LICENSE
tdbudget/__init__.py
tdbudget/__version__.py
tdbudget/conf.json
tdbudget/keys.py
tdbudget/monthly.py
tdbudget/tdbudget.py
tdbudget-0.5.0.dist-info/METADATA
tdbudget-0.5.0.dist-info/WHEEL
tdbudget-0.5.0.dist-info/entry_points.txt
tdbudget-0.5.0.dist-info/top_level.txt
tdbudget-0.5.0.dist-info/RECORD
