Metadata-Version: 2.1
Name: tdbudget
Version: 0.5.0
Summary: A simple command line interface for managing a budget.
Home-page: UNKNOWN
Author: Thomas Spader
Author-email: thomas.spader@gmail.com
License: UNKNOWN
Platform: UNKNOWN
Classifier: License :: OSI Approved :: MIT License
Classifier: Programming Language :: Python
Classifier: Programming Language :: Python :: 3
Classifier: Programming Language :: Python :: 3.6
Classifier: Programming Language :: Python :: Implementation :: CPython
Classifier: Programming Language :: Python :: Implementation :: PyPy
Requires-Python: >=3.6.0
Requires-Dist: click
